odoo/addons/purchase_partner_approval/README.rst
odoo/addons/purchase_partner_approval/__init__.py
odoo/addons/purchase_partner_approval/__manifest__.py
odoo/addons/purchase_partner_approval/data/exception_rule.xml
odoo/addons/purchase_partner_approval/data/init_puchase_ok.xml
odoo/addons/purchase_partner_approval/i18n/es.po
odoo/addons/purchase_partner_approval/i18n/it.po
odoo/addons/purchase_partner_approval/i18n/purchase_partner_approval.pot
odoo/addons/purchase_partner_approval/models/__init__.py
odoo/addons/purchase_partner_approval/models/purchase_order.py
odoo/addons/purchase_partner_approval/models/res_partner.py
odoo/addons/purchase_partner_approval/models/res_partner_stage.py
odoo/addons/purchase_partner_approval/readme/CONFIGURE.rst
odoo/addons/purchase_partner_approval/readme/CONTRIBUTORS.rst
odoo/addons/purchase_partner_approval/readme/DESCRIPTION.rst
odoo/addons/purchase_partner_approval/readme/USAGE.rst
odoo/addons/purchase_partner_approval/static/description/icon.png
odoo/addons/purchase_partner_approval/static/description/index.html
odoo/addons/purchase_partner_approval/tests/__init__.py
odoo/addons/purchase_partner_approval/tests/test_product_approval.py
odoo/addons/purchase_partner_approval/views/res_partner.xml
odoo/addons/purchase_partner_approval/views/res_partner_stage.xml
odoo14_addon_purchase_partner_approval-14.0.1.0.1.dev6.dist-info/METADATA
odoo14_addon_purchase_partner_approval-14.0.1.0.1.dev6.dist-info/WHEEL
odoo14_addon_purchase_partner_approval-14.0.1.0.1.dev6.dist-info/top_level.txt
odoo14_addon_purchase_partner_approval-14.0.1.0.1.dev6.dist-info/RECORD
